{
  "@id": "https://data.datatourisme.fr/3/0321f644-9b8d-3255-b36d-76710f8f148c",
  "dc:identifier": "LOICHA0101290998",
  "@type": [
    "schema:LocalBusiness",
    "EquestrianCenter",
    "PlaceOfInterest",
    "PointOfInterest",
    "SportsAndLeisurePlace"
  ],
  "rdfs:label": {
    "fr": [
      "Poney Club Bucey"
    ]
  },
  "creationDate": "2017-07-04",
  "hasBeenCreatedBy": {
    "@id": "https://data.datatourisme.fr/ef971846-61e2-3e36-a7ba-8f9546ebfbd3",
    "schema:address": [
      {
        "@id": "https://data.datatourisme.fr/d50a9103-ca79-365f-aad8-705ee9739035",
        "schema:addressLocality": "Troyes",
        "schema:postalCode": "10000",
        "schema:streetAddress": [
          "16 Rue Aristide Briand"
        ],
        "@type": [
          "schema:PostalAddress",
          "PostalAddress"
        ],
        "hasAddressCity": {
          "@id": "kb:10387",
          "@type": [
            "City"
          ],
          "rdfs:label": {
            "de": [
              "Troyes"
            ],
            "pt": [
              "Troyes"
            ],
            "en": [
              "Troyes"
            ],
            "it": [
              "Troyes"
            ],
            "fr": [
              "Troyes"
            ],
            "nl": [
              "Troyes"
            ],
            "es": [
              "Troyes"
            ]
          },
          "insee": "10387",
          "isPartOfDepartment": {
            "@id": "kb:France4410",
            "@type": [
              "Department"
            ],
            "rdfs:label": {
              "de": [
                "Aube"
              ],
              "pt": [
                "Aube"
              ],
              "en": [
                "Aube"
              ],
              "it": [
                "Aube"
              ],
              "fr": [
                "Aube"
              ],
              "nl": [
                "Aube"
              ],
              "es": [
                "Aube"
              ]
            },
            "insee": "10",
            "isPartOfRegion": {
              "@id": "kb:France44",
              "@type": [
                "Region"
              ],
              "rdfs:label": {
                "de": [
                  "Grand Est"
                ],
                "pt": [
                  "Grand Est"
                ],
                "en": [
                  "Grand Est"
                ],
                "it": [
                  "Grand Est"
                ],
                "fr": [
                  "Grand Est"
                ],
                "nl": [
                  "Grand Est"
                ],
                "es": [
                  "Grand Est"
                ]
              },
              "insee": "44",
              "isPartOfCountry": {
                "@id": "kb:France",
                "@type": [
                  "schema:Country"
                ],
                "rdfs:label": {
                  "de": [
                    "France",
                    "Frankreich"
                  ],
                  "pt": [
                    "França",
                    "France"
                  ],
                  "en": [
                    "France"
                  ],
                  "it": [
                    "France",
                    "Francia"
                  ],
                  "fr": [
                    "France"
                  ],
                  "nl": [
                    "France",
                    "Frankrijk"
                  ],
                  "es": [
                    "France",
                    "Francia"
                  ]
                }
              }
            }
          }
        }
      }
    ],
    "schema:email": [
      "contact@troyeslachampagne.com"
    ],
    "schema:legalName": "Office de Tourisme Troyes la Champagne",
    "@type": [
      "schema:Organization",
      "foaf:Agent",
      "Agent"
    ],
    "foaf:homepage": [
      "https://www.troyeslachampagne.com/"
    ]
  },
  "hasBeenPublishedBy": [
    {
      "@id": "https://data.datatourisme.fr/9764ff09-9e3c-36ba-9c61-65a81839dc85",
      "schema:email": [
        "bonjour@aube-champagne.com"
      ],
      "schema:legalName": "Aube en Champagne Tourisme",
      "schema:telephone": [
        "+33 3 25 42 50 00"
      ],
      "@type": [
        "schema:Organization",
        "foaf:Agent",
        "Agent"
      ],
      "foaf:homepage": [
        "https://www.aube-champagne.com/"
      ]
    }
  ],
  "hasContact": [
    {
      "@id": "https://data.datatourisme.fr/43804eae-0532-3045-81de-786188c5cd7e",
      "schema:legalName": "Poney Club Bucey",
      "schema:telephone": [
        "+33 6 83 49 69 81"
      ],
      "@type": [
        "schema:Organization",
        "foaf:Agent",
        "Agent"
      ],
      "foaf:homepage": [
        "https://www.facebook.com/poneyclubdebucey/"
      ]
    }
  ],
  "hasDescription": [
    {
      "@id": "https://data.datatourisme.fr/d697c9df-63fe-3155-8d24-4ea2a334ef86",
      "dc:description": {
        "de": [
          "EQUI'PASSION, der Pony-Club von Bucey en Othe. \n\n- Reitunterricht in Gruppen oder Einzelpersonen, theoretisch und praktisch\n- Baby-Reiter\n- Ausbildungskurse - Galoppieren - Reiten - Wanderungen - Dressur - Springen \n- Pony-Spiele - Equifun - Equifeel - Jäger - Trec\n- C50 - Vollpension \n- Biwaks - Reiter-Etappe"
        ],
        "en": [
          "EQUI'PASSION, the pony club of Bucey en Othe. \n\n- Riding lessons in groups or individuals, theoretical & practical\n- Baby riders\n- Training courses - galloping - rides - hikes - dressage - show jumping \n- Pony games- Equifun - Equifeel - hunter - trec\n- C50 - full board \n- Bivouacs - Rider stage"
        ],
        "it": [
          "EQUI'PASSION, il pony club di Bucey en Othe.\n\n- Lezioni di equitazione di gruppo o individuali, teoria e pratica\n- Baby cavalieri\n- Corsi - Passaggio al galoppo - Giri - Passeggiate - Dressage - Salto\n- Pony games - Equifun - Equifeel - hunter - trec\n- C50 - pensione completa\n- Bivacchi - Sosta per i cavalieri"
        ],
        "fr": [
          "EQUI'PASSION, le poney club de Bucey en Othe. \n\n- Cours d'équitation en groupes ou individuels, théoriques & pratiques\n- Baby cavaliers\n- Stages - passages de galops - balades - randonnées - dressage - saut d'obstacles \n- Pony games- Equifun - Equifeel - hunter - trec\n- C50 - pension complète \n- Bivouacs - Etape cavaliers"
        ],
        "es": [
          "EQUI'PASSION, el club de ponis de Bucey en Othe.\n\n- Clases de equitación en grupo o individuales, teóricas y prácticas\n- Baby jinetes\n- Cursos - Paso de galope - Paseos - Paseos - Doma - Salto\n- Juegos de ponis - Equifun - Equifeel - cazador - trec\n- C50 - pensión completa\n- Vivacs - Escala para jinetes"
        ],
        "nl": [
          "EQUI'PASSION, de ponyclub van Bucey en Othe. \n\n- Paardrijlessen in groep of individueel, theoretisch & praktisch\n- Baby ruiters\n- Trainingen - galopperen - ritten - wandelingen - dressuur - springen \n- Pony spelletjes- Equifun - Equifeel - jager - trec\n- C50 - volpension \n- Bivakmutsen - Ruiteretappe"
        ]
      },
      "@type": [
        "Description"
      ],
      "hasTranslatedProperty": [
        {
          "@id": "https://data.datatourisme.fr/6fdf64ba-534f-349c-a05c-1c99a8a3864b",
          "dc:contributor": [
            "https://api.deepl.com/v2/translate"
          ],
          "rdf:language": [
            "es"
          ],
          "rdf:predicate": [
            {
              "@id": "dc:description"
            }
          ]
        },
        {
          "@id": "https://data.datatourisme.fr/a78c902e-db28-3315-80b8-e141b5c5607c",
          "dc:contributor": [
            "https://api.deepl.com/v2/translate"
          ],
          "rdf:language": [
            "it"
          ],
          "rdf:predicate": [
            {
              "@id": "dc:description"
            }
          ]
        }
      ]
    }
  ],
  "hasExternalReference": [
    {
      "@id": "https://data.datatourisme.fr/17bce7b2-d83a-ead9-2a38-7eb48128a021",
      "@type": [
        "ExternalReference"
      ],
      "hasExternalIdentifier": "WX7RZ6HYX5WE",
      "hasExternalPlatform": [
        {
          "@id": "kb:ReferentielNationalBatiments",
          "@type": [
            "ExternalPlatform"
          ],
          "rdfs:comment": {
            "de": [
              "Ein digitaler öffentlicher Dienst, der eine nationale Gebäude-Referenz erstellt."
            ],
            "pt": [
              "Serviço público digital que cria uma referência nacional de edifícios."
            ],
            "en": [
              "A digital public service creating a national building reference."
            ],
            "it": [
              "Servizio pubblico digitale che crea un riferimento nazionale degli edifici."
            ],
            "fr": [
              "Service public numérique créant une référence nationale du bâtiment."
            ],
            "es": [
              "Un servicio público digital que crea una referencia nacional de edificios."
            ],
            "nl": [
              "Een digitale openbare dienst die een nationale gebouwreferentie creëert."
            ]
          },
          "rdfs:label": {
            "de": [
              "Nationales Gebäude-Referenzsystem"
            ],
            "pt": [
              "Normas nacionais de construção"
            ],
            "en": [
              "National Building Standards"
            ],
            "it": [
              "Standard edilizi nazionali"
            ],
            "fr": [
              "Référentiel National des Bâtiments"
            ],
            "es": [
              "Normas nacionales de construcción"
            ],
            "nl": [
              "Nationale bouwnorm"
            ]
          },
          "hasExternalPlatformUrl": "https://rnb.beta.gouv.fr"
        }
      ]
    },
    {
      "@id": "https://data.datatourisme.fr/25f68d42-0dec-1cc6-bb81-0ee148a8e58d",
      "@type": [
        "ExternalReference"
      ],
      "hasExternalIdentifier": "352T87ATA8QC",
      "hasExternalPlatform": [
        {
          "@id": "kb:ReferentielNationalBatiments",
          "@type": [
            "ExternalPlatform"
          ],
          "rdfs:comment": {
            "de": [
              "Ein digitaler öffentlicher Dienst, der eine nationale Gebäude-Referenz erstellt."
            ],
            "pt": [
              "Serviço público digital que cria uma referência nacional de edifícios."
            ],
            "en": [
              "A digital public service creating a national building reference."
            ],
            "it": [
              "Servizio pubblico digitale che crea un riferimento nazionale degli edifici."
            ],
            "fr": [
              "Service public numérique créant une référence nationale du bâtiment."
            ],
            "es": [
              "Un servicio público digital que crea una referencia nacional de edificios."
            ],
            "nl": [
              "Een digitale openbare dienst die een nationale gebouwreferentie creëert."
            ]
          },
          "rdfs:label": {
            "de": [
              "Nationales Gebäude-Referenzsystem"
            ],
            "pt": [
              "Normas nacionais de construção"
            ],
            "en": [
              "National Building Standards"
            ],
            "it": [
              "Standard edilizi nazionali"
            ],
            "fr": [
              "Référentiel National des Bâtiments"
            ],
            "es": [
              "Normas nacionales de construcción"
            ],
            "nl": [
              "Nationale bouwnorm"
            ]
          },
          "hasExternalPlatformUrl": "https://rnb.beta.gouv.fr"
        }
      ]
    },
    {
      "@id": "https://data.datatourisme.fr/8c9edf3f-6e52-0fa3-ea03-e8349079c26a",
      "@type": [
        "ExternalReference"
      ],
      "hasExternalIdentifier": "5X4VME6G9ZR6",
      "hasExternalPlatform": [
        {
          "@id": "kb:ReferentielNationalBatiments",
          "@type": [
            "ExternalPlatform"
          ],
          "rdfs:comment": {
            "de": [
              "Ein digitaler öffentlicher Dienst, der eine nationale Gebäude-Referenz erstellt."
            ],
            "pt": [
              "Serviço público digital que cria uma referência nacional de edifícios."
            ],
            "en": [
              "A digital public service creating a national building reference."
            ],
            "it": [
              "Servizio pubblico digitale che crea un riferimento nazionale degli edifici."
            ],
            "fr": [
              "Service public numérique créant une référence nationale du bâtiment."
            ],
            "es": [
              "Un servicio público digital que crea una referencia nacional de edificios."
            ],
            "nl": [
              "Een digitale openbare dienst die een nationale gebouwreferentie creëert."
            ]
          },
          "rdfs:label": {
            "de": [
              "Nationales Gebäude-Referenzsystem"
            ],
            "pt": [
              "Normas nacionais de construção"
            ],
            "en": [
              "National Building Standards"
            ],
            "it": [
              "Standard edilizi nazionali"
            ],
            "fr": [
              "Référentiel National des Bâtiments"
            ],
            "es": [
              "Normas nacionales de construcción"
            ],
            "nl": [
              "Nationale bouwnorm"
            ]
          },
          "hasExternalPlatformUrl": "https://rnb.beta.gouv.fr"
        }
      ]
    }
  ],
  "hasMainRepresentation": [
    {
      "@id": "https://data.datatourisme.fr/758c53f3-5002-3e21-8eda-de892953a511",
      "ebucore:hasAnnotation": [
        {
          "@id": "https://data.datatourisme.fr/3a95d5fb-9607-36c6-83da-d11b1bdb163b",
          "ebucore:title": {
            "fr": [
              "IMG_2901.JPG"
            ]
          },
          "@type": [
            "ebucore:Annotation"
          ],
          "credits": [
            "Clara Gouin - Troyes La Champagne Tourisme"
          ]
        }
      ],
      "ebucore:hasRelatedResource": [
        {
          "@id": "https://data.datatourisme.fr/7321192e-a47e-31fb-b297-5e9467841562",
          "ebucore:hasMimeType": [
            {
              "@id": "kb:JPEG",
              "@type": [
                "ebucore:MimeType"
              ],
              "rdfs:comment": {
                "de": [
                  "JPEG-Bild"
                ],
                "pt": [
                  "Imagem JPEG"
                ],
                "en": [
                  "JPEG image file"
                ],
                "it": [
                  "Immagine JPEG"
                ],
                "fr": [
                  "Image JPEG"
                ],
                "nl": [
                  "JPEG-afbeelding"
                ],
                "es": [
                  "Imagen JPEG"
                ]
              },
              "rdfs:label": {
                "de": [
                  "image/jpeg"
                ],
                "pt": [
                  "image/jpeg"
                ],
                "en": [
                  "image/jpeg"
                ],
                "it": [
                  "image/jpeg"
                ],
                "fr": [
                  "image/jpeg"
                ],
                "nl": [
                  "image/jpeg"
                ],
                "es": [
                  "image/jpeg"
                ]
              }
            },
            {
              "@id": "kb:PNG",
              "@type": [
                "ebucore:MimeType"
              ],
              "rdfs:comment": {
                "de": [
                  "PDF-Bild"
                ],
                "pt": [
                  "Imagem PDF"
                ],
                "en": [
                  "PDF image file"
                ],
                "it": [
                  "Immagine PDF"
                ],
                "fr": [
                  "Image PDF"
                ],
                "nl": [
                  "Pdf-afbeelding"
                ],
                "es": [
                  "Imagen PDF"
                ]
              },
              "rdfs:label": {
                "de": [
                  "image/png"
                ],
                "pt": [
                  "image/png"
                ],
                "en": [
                  "image/png"
                ],
                "it": [
                  "image/png"
                ],
                "fr": [
                  "image/png"
                ],
                "nl": [
                  "image/png"
                ],
                "es": [
                  "image/png"
                ]
              }
            }
          ],
          "ebucore:locator": [
            "http://medias.tourism-system.com/d/3/634154_img_2901.jpg"
          ],
          "@type": [
            "ebucore:Resource"
          ]
        }
      ],
      "@type": [
        "ebucore:EditorialObject"
      ]
    }
  ],
  "hasRepresentation": [
    {
      "@id": "https://data.datatourisme.fr/1d0c2212-3ec4-3a59-9414-d80e019dbb27",
      "ebucore:hasAnnotation": [
        {
          "@id": "https://data.datatourisme.fr/9f75e7ea-d04a-3f02-96ac-fa661a0ff839",
          "ebucore:title": {
            "fr": [
              "IMG_2896.JPG"
            ]
          },
          "@type": [
            "ebucore:Annotation"
          ],
          "credits": [
            "Clara Gouin - Troyes La Champagne Tourisme"
          ]
        }
      ],
      "ebucore:hasRelatedResource": [
        {
          "@id": "https://data.datatourisme.fr/043cdab6-a273-324d-a768-b33a35c546b1",
          "ebucore:hasMimeType": [
            {
              "@id": "kb:JPEG",
              "@type": [
                "ebucore:MimeType"
              ],
              "rdfs:comment": {
                "de": [
                  "JPEG-Bild"
                ],
                "pt": [
                  "Imagem JPEG"
                ],
                "en": [
                  "JPEG image file"
                ],
                "it": [
                  "Immagine JPEG"
                ],
                "fr": [
                  "Image JPEG"
                ],
                "nl": [
                  "JPEG-afbeelding"
                ],
                "es": [
                  "Imagen JPEG"
                ]
              },
              "rdfs:label": {
                "de": [
                  "image/jpeg"
                ],
                "pt": [
                  "image/jpeg"
                ],
                "en": [
                  "image/jpeg"
                ],
                "it": [
                  "image/jpeg"
                ],
                "fr": [
                  "image/jpeg"
                ],
                "nl": [
                  "image/jpeg"
                ],
                "es": [
                  "image/jpeg"
                ]
              }
            },
            {
              "@id": "kb:PNG",
              "@type": [
                "ebucore:MimeType"
              ],
              "rdfs:comment": {
                "de": [
                  "PDF-Bild"
                ],
                "pt": [
                  "Imagem PDF"
                ],
                "en": [
                  "PDF image file"
                ],
                "it": [
                  "Immagine PDF"
                ],
                "fr": [
                  "Image PDF"
                ],
                "nl": [
                  "Pdf-afbeelding"
                ],
                "es": [
                  "Imagen PDF"
                ]
              },
              "rdfs:label": {
                "de": [
                  "image/png"
                ],
                "pt": [
                  "image/png"
                ],
                "en": [
                  "image/png"
                ],
                "it": [
                  "image/png"
                ],
                "fr": [
                  "image/png"
                ],
                "nl": [
                  "image/png"
                ],
                "es": [
                  "image/png"
                ]
              }
            }
          ],
          "ebucore:locator": [
            "http://medias.tourism-system.com/1/4/634155_img_2896.jpg"
          ],
          "@type": [
            "ebucore:Resource"
          ]
        }
      ],
      "@type": [
        "ebucore:EditorialObject"
      ]
    },
    {
      "@id": "https://data.datatourisme.fr/38ec4e25-8420-34c3-a147-83c89d05c3ec",
      "ebucore:hasAnnotation": [
        {
          "@id": "https://data.datatourisme.fr/aadf338e-b4be-30b9-bb95-5784f7bb0589",
          "ebucore:title": {
            "fr": [
              "IMG_2898.JPG"
            ]
          },
          "@type": [
            "ebucore:Annotation"
          ],
          "credits": [
            "Clara Gouin - Troyes La Champagne Tourisme"
          ]
        }
      ],
      "ebucore:hasRelatedResource": [
        {
          "@id": "https://data.datatourisme.fr/0cc9e4fe-9919-3759-adac-dd91cb119b82",
          "ebucore:hasMimeType": [
            {
              "@id": "kb:JPEG",
              "@type": [
                "ebucore:MimeType"
              ],
              "rdfs:comment": {
                "de": [
                  "JPEG-Bild"
                ],
                "pt": [
                  "Imagem JPEG"
                ],
                "en": [
                  "JPEG image file"
                ],
                "it": [
                  "Immagine JPEG"
                ],
                "fr": [
                  "Image JPEG"
                ],
                "nl": [
                  "JPEG-afbeelding"
                ],
                "es": [
                  "Imagen JPEG"
                ]
              },
              "rdfs:label": {
                "de": [
                  "image/jpeg"
                ],
                "pt": [
                  "image/jpeg"
                ],
                "en": [
                  "image/jpeg"
                ],
                "it": [
                  "image/jpeg"
                ],
                "fr": [
                  "image/jpeg"
                ],
                "nl": [
                  "image/jpeg"
                ],
                "es": [
                  "image/jpeg"
                ]
              }
            },
            {
              "@id": "kb:PNG",
              "@type": [
                "ebucore:MimeType"
              ],
              "rdfs:comment": {
                "de": [
                  "PDF-Bild"
                ],
                "pt": [
                  "Imagem PDF"
                ],
                "en": [
                  "PDF image file"
                ],
                "it": [
                  "Immagine PDF"
                ],
                "fr": [
                  "Image PDF"
                ],
                "nl": [
                  "Pdf-afbeelding"
                ],
                "es": [
                  "Imagen PDF"
                ]
              },
              "rdfs:label": {
                "de": [
                  "image/png"
                ],
                "pt": [
                  "image/png"
                ],
                "en": [
                  "image/png"
                ],
                "it": [
                  "image/png"
                ],
                "fr": [
                  "image/png"
                ],
                "nl": [
                  "image/png"
                ],
                "es": [
                  "image/png"
                ]
              }
            }
          ],
          "ebucore:locator": [
            "http://medias.tourism-system.com/c/6/634159_img_2898.jpg"
          ],
          "@type": [
            "ebucore:Resource"
          ]
        }
      ],
      "@type": [
        "ebucore:EditorialObject"
      ]
    },
    {
      "@id": "https://data.datatourisme.fr/4a560224-0da9-3fe8-af40-15c8793126fe",
      "ebucore:hasAnnotation": [
        {
          "@id": "https://data.datatourisme.fr/2ba0ade7-c0dc-320a-b139-baf4fdeeddf4",
          "ebucore:title": {
            "fr": [
              "IMG_2897.JPG"
            ]
          },
          "@type": [
            "ebucore:Annotation"
          ],
          "credits": [
            "Clara Gouin - Troyes La Champagne Tourisme"
          ]
        }
      ],
      "ebucore:hasRelatedResource": [
        {
          "@id": "https://data.datatourisme.fr/a96bd6b0-7c88-308a-8b18-c045a61db0ec",
          "ebucore:hasMimeType": [
            {
              "@id": "kb:JPEG",
              "@type": [
                "ebucore:MimeType"
              ],
              "rdfs:comment": {
                "de": [
                  "JPEG-Bild"
                ],
                "pt": [
                  "Imagem JPEG"
                ],
                "en": [
                  "JPEG image file"
                ],
                "it": [
                  "Immagine JPEG"
                ],
                "fr": [
                  "Image JPEG"
                ],
                "nl": [
                  "JPEG-afbeelding"
                ],
                "es": [
                  "Imagen JPEG"
                ]
              },
              "rdfs:label": {
                "de": [
                  "image/jpeg"
                ],
                "pt": [
                  "image/jpeg"
                ],
                "en": [
                  "image/jpeg"
                ],
                "it": [
                  "image/jpeg"
                ],
                "fr": [
                  "image/jpeg"
                ],
                "nl": [
                  "image/jpeg"
                ],
                "es": [
                  "image/jpeg"
                ]
              }
            },
            {
              "@id": "kb:PNG",
              "@type": [
                "ebucore:MimeType"
              ],
              "rdfs:comment": {
                "de": [
                  "PDF-Bild"
                ],
                "pt": [
                  "Imagem PDF"
                ],
                "en": [
                  "PDF image file"
                ],
                "it": [
                  "Immagine PDF"
                ],
                "fr": [
                  "Image PDF"
                ],
                "nl": [
                  "Pdf-afbeelding"
                ],
                "es": [
                  "Imagen PDF"
                ]
              },
              "rdfs:label": {
                "de": [
                  "image/png"
                ],
                "pt": [
                  "image/png"
                ],
                "en": [
                  "image/png"
                ],
                "it": [
                  "image/png"
                ],
                "fr": [
                  "image/png"
                ],
                "nl": [
                  "image/png"
                ],
                "es": [
                  "image/png"
                ]
              }
            }
          ],
          "ebucore:locator": [
            "http://medias.tourism-system.com/d/2/634158_img_2897.jpg"
          ],
          "@type": [
            "ebucore:Resource"
          ]
        }
      ],
      "@type": [
        "ebucore:EditorialObject"
      ]
    },
    {
      "@id": "https://data.datatourisme.fr/758c53f3-5002-3e21-8eda-de892953a511",
      "ebucore:hasAnnotation": [
        {
          "@id": "https://data.datatourisme.fr/3a95d5fb-9607-36c6-83da-d11b1bdb163b",
          "ebucore:title": {
            "fr": [
              "IMG_2901.JPG"
            ]
          },
          "@type": [
            "ebucore:Annotation"
          ],
          "credits": [
            "Clara Gouin - Troyes La Champagne Tourisme"
          ]
        }
      ],
      "ebucore:hasRelatedResource": [
        {
          "@id": "https://data.datatourisme.fr/7321192e-a47e-31fb-b297-5e9467841562",
          "ebucore:hasMimeType": [
            {
              "@id": "kb:JPEG",
              "@type": [
                "ebucore:MimeType"
              ],
              "rdfs:comment": {
                "de": [
                  "JPEG-Bild"
                ],
                "pt": [
                  "Imagem JPEG"
                ],
                "en": [
                  "JPEG image file"
                ],
                "it": [
                  "Immagine JPEG"
                ],
                "fr": [
                  "Image JPEG"
                ],
                "nl": [
                  "JPEG-afbeelding"
                ],
                "es": [
                  "Imagen JPEG"
                ]
              },
              "rdfs:label": {
                "de": [
                  "image/jpeg"
                ],
                "pt": [
                  "image/jpeg"
                ],
                "en": [
                  "image/jpeg"
                ],
                "it": [
                  "image/jpeg"
                ],
                "fr": [
                  "image/jpeg"
                ],
                "nl": [
                  "image/jpeg"
                ],
                "es": [
                  "image/jpeg"
                ]
              }
            },
            {
              "@id": "kb:PNG",
              "@type": [
                "ebucore:MimeType"
              ],
              "rdfs:comment": {
                "de": [
                  "PDF-Bild"
                ],
                "pt": [
                  "Imagem PDF"
                ],
                "en": [
                  "PDF image file"
                ],
                "it": [
                  "Immagine PDF"
                ],
                "fr": [
                  "Image PDF"
                ],
                "nl": [
                  "Pdf-afbeelding"
                ],
                "es": [
                  "Imagen PDF"
                ]
              },
              "rdfs:label": {
                "de": [
                  "image/png"
                ],
                "pt": [
                  "image/png"
                ],
                "en": [
                  "image/png"
                ],
                "it": [
                  "image/png"
                ],
                "fr": [
                  "image/png"
                ],
                "nl": [
                  "image/png"
                ],
                "es": [
                  "image/png"
                ]
              }
            }
          ],
          "ebucore:locator": [
            "http://medias.tourism-system.com/d/3/634154_img_2901.jpg"
          ],
          "@type": [
            "ebucore:Resource"
          ]
        }
      ],
      "@type": [
        "ebucore:EditorialObject"
      ]
    },
    {
      "@id": "https://data.datatourisme.fr/918c067e-1235-3511-8100-a38598dc49cd",
      "ebucore:hasAnnotation": [
        {
          "@id": "https://data.datatourisme.fr/20c10de6-7248-36c9-aaad-bb085e06594d",
          "ebucore:title": {
            "fr": [
              "IMG_2899.JPG"
            ]
          },
          "@type": [
            "ebucore:Annotation"
          ],
          "credits": [
            "Clara Gouin - Troyes La Champagne Tourisme"
          ]
        }
      ],
      "ebucore:hasRelatedResource": [
        {
          "@id": "https://data.datatourisme.fr/ef00f56f-c9d0-3f19-95f7-e170e03b0be2",
          "ebucore:hasMimeType": [
            {
              "@id": "kb:JPEG",
              "@type": [
                "ebucore:MimeType"
              ],
              "rdfs:comment": {
                "de": [
                  "JPEG-Bild"
                ],
                "pt": [
                  "Imagem JPEG"
                ],
                "en": [
                  "JPEG image file"
                ],
                "it": [
                  "Immagine JPEG"
                ],
                "fr": [
                  "Image JPEG"
                ],
                "nl": [
                  "JPEG-afbeelding"
                ],
                "es": [
                  "Imagen JPEG"
                ]
              },
              "rdfs:label": {
                "de": [
                  "image/jpeg"
                ],
                "pt": [
                  "image/jpeg"
                ],
                "en": [
                  "image/jpeg"
                ],
                "it": [
                  "image/jpeg"
                ],
                "fr": [
                  "image/jpeg"
                ],
                "nl": [
                  "image/jpeg"
                ],
                "es": [
                  "image/jpeg"
                ]
              }
            },
            {
              "@id": "kb:PNG",
              "@type": [
                "ebucore:MimeType"
              ],
              "rdfs:comment": {
                "de": [
                  "PDF-Bild"
                ],
                "pt": [
                  "Imagem PDF"
                ],
                "en": [
                  "PDF image file"
                ],
                "it": [
                  "Immagine PDF"
                ],
                "fr": [
                  "Image PDF"
                ],
                "nl": [
                  "Pdf-afbeelding"
                ],
                "es": [
                  "Imagen PDF"
                ]
              },
              "rdfs:label": {
                "de": [
                  "image/png"
                ],
                "pt": [
                  "image/png"
                ],
                "en": [
                  "image/png"
                ],
                "it": [
                  "image/png"
                ],
                "fr": [
                  "image/png"
                ],
                "nl": [
                  "image/png"
                ],
                "es": [
                  "image/png"
                ]
              }
            }
          ],
          "ebucore:locator": [
            "http://medias.tourism-system.com/d/3/634157_img_2899.jpg"
          ],
          "@type": [
            "ebucore:Resource"
          ]
        }
      ],
      "@type": [
        "ebucore:EditorialObject"
      ]
    },
    {
      "@id": "https://data.datatourisme.fr/ea95146c-225b-3d81-b9b3-aebad45d169c",
      "ebucore:hasAnnotation": [
        {
          "@id": "https://data.datatourisme.fr/cc2bd611-b51a-31ec-9720-923e16f39371",
          "ebucore:title": {
            "fr": [
              "IMG_2900.JPG"
            ]
          },
          "@type": [
            "ebucore:Annotation"
          ],
          "credits": [
            "Clara Gouin - Troyes La Champagne Tourisme"
          ]
        }
      ],
      "ebucore:hasRelatedResource": [
        {
          "@id": "https://data.datatourisme.fr/14b2c79e-75e3-302a-a136-c43fac4efe9a",
          "ebucore:hasMimeType": [
            {
              "@id": "kb:JPEG",
              "@type": [
                "ebucore:MimeType"
              ],
              "rdfs:comment": {
                "de": [
                  "JPEG-Bild"
                ],
                "pt": [
                  "Imagem JPEG"
                ],
                "en": [
                  "JPEG image file"
                ],
                "it": [
                  "Immagine JPEG"
                ],
                "fr": [
                  "Image JPEG"
                ],
                "nl": [
                  "JPEG-afbeelding"
                ],
                "es": [
                  "Imagen JPEG"
                ]
              },
              "rdfs:label": {
                "de": [
                  "image/jpeg"
                ],
                "pt": [
                  "image/jpeg"
                ],
                "en": [
                  "image/jpeg"
                ],
                "it": [
                  "image/jpeg"
                ],
                "fr": [
                  "image/jpeg"
                ],
                "nl": [
                  "image/jpeg"
                ],
                "es": [
                  "image/jpeg"
                ]
              }
            },
            {
              "@id": "kb:PNG",
              "@type": [
                "ebucore:MimeType"
              ],
              "rdfs:comment": {
                "de": [
                  "PDF-Bild"
                ],
                "pt": [
                  "Imagem PDF"
                ],
                "en": [
                  "PDF image file"
                ],
                "it": [
                  "Immagine PDF"
                ],
                "fr": [
                  "Image PDF"
                ],
                "nl": [
                  "Pdf-afbeelding"
                ],
                "es": [
                  "Imagen PDF"
                ]
              },
              "rdfs:label": {
                "de": [
                  "image/png"
                ],
                "pt": [
                  "image/png"
                ],
                "en": [
                  "image/png"
                ],
                "it": [
                  "image/png"
                ],
                "fr": [
                  "image/png"
                ],
                "nl": [
                  "image/png"
                ],
                "es": [
                  "image/png"
                ]
              }
            }
          ],
          "ebucore:locator": [
            "http://medias.tourism-system.com/9/8/634156_img_2900.jpg"
          ],
          "@type": [
            "ebucore:Resource"
          ]
        }
      ],
      "@type": [
        "ebucore:EditorialObject"
      ]
    }
  ],
  "isLocatedAt": [
    {
      "@id": "https://data.datatourisme.fr/8fe78c70-2871-3b0b-8689-6f5123eec155",
      "schema:address": [
        {
          "@id": "https://data.datatourisme.fr/5eece26f-1ae0-3156-ae96-3b79db11660c",
          "schema:addressLocality": "Bucey-en-Othe",
          "schema:postalCode": "10190",
          "schema:streetAddress": [
            "17 rue des Combattants d'AFN"
          ],
          "@type": [
            "schema:PostalAddress",
            "PostalAddress"
          ],
          "hasAddressCity": {
            "@id": "kb:10066",
            "@type": [
              "City"
            ],
            "rdfs:label": {
              "de": [
                "Bucey-en-Othe"
              ],
              "pt": [
                "Bucey-en-Othe"
              ],
              "en": [
                "Bucey-en-Othe"
              ],
              "it": [
                "Bucey-en-Othe"
              ],
              "fr": [
                "Bucey-en-Othe"
              ],
              "nl": [
                "Bucey-en-Othe"
              ],
              "es": [
                "Bucey-en-Othe"
              ]
            },
            "insee": "10066",
            "isPartOfDepartment": {
              "@id": "kb:France4410",
              "@type": [
                "Department"
              ],
              "rdfs:label": {
                "de": [
                  "Aube"
                ],
                "pt": [
                  "Aube"
                ],
                "en": [
                  "Aube"
                ],
                "it": [
                  "Aube"
                ],
                "fr": [
                  "Aube"
                ],
                "nl": [
                  "Aube"
                ],
                "es": [
                  "Aube"
                ]
              },
              "insee": "10",
              "isPartOfRegion": {
                "@id": "kb:France44",
                "@type": [
                  "Region"
                ],
                "rdfs:label": {
                  "de": [
                    "Grand Est"
                  ],
                  "pt": [
                    "Grand Est"
                  ],
                  "en": [
                    "Grand Est"
                  ],
                  "it": [
                    "Grand Est"
                  ],
                  "fr": [
                    "Grand Est"
                  ],
                  "nl": [
                    "Grand Est"
                  ],
                  "es": [
                    "Grand Est"
                  ]
                },
                "insee": "44",
                "isPartOfCountry": {
                  "@id": "kb:France",
                  "@type": [
                    "schema:Country"
                  ],
                  "rdfs:label": {
                    "de": [
                      "France",
                      "Frankreich"
                    ],
                    "pt": [
                      "França",
                      "France"
                    ],
                    "en": [
                      "France"
                    ],
                    "it": [
                      "France",
                      "Francia"
                    ],
                    "fr": [
                      "France"
                    ],
                    "nl": [
                      "France",
                      "Frankrijk"
                    ],
                    "es": [
                      "France",
                      "Francia"
                    ]
                  }
                }
              }
            }
          }
        }
      ],
      "schema:geo": {
        "@id": "https://data.datatourisme.fr/6f4a06a6-e19d-33f6-bf56-f779bf116a22",
        "schema:latitude": "48.258889",
        "schema:longitude": "3.8624654",
        "@type": [
          "schema:GeoCoordinates"
        ]
      },
      "schema:openingHoursSpecification": [
        {
          "@id": "https://data.datatourisme.fr/5962de29-6765-3288-a006-419cf87dd97d",
          "schema:closes": "18:00:00",
          "schema:dayOfWeek": [
            {
              "@id": "schema:Tuesday",
              "@type": [
                "schema:DayOfWeek"
              ],
              "rdfs:label": {
                "de": [
                  "Dienstag"
                ],
                "pt": [
                  "Terça-feira"
                ],
                "en": [
                  "Tuesday"
                ],
                "it": [
                  "Martedì"
                ],
                "fr": [
                  "Mardi"
                ],
                "es": [
                  "Martes"
                ],
                "nl": [
                  "Dinsdag"
                ]
              }
            }
          ],
          "schema:opens": "09:00:00",
          "schema:validFrom": "2024-01-01T09:00:00",
          "schema:validThrough": "2024-12-31T18:00:00",
          "@type": [
            "schema:OpeningHoursSpecification"
          ]
        },
        {
          "@id": "https://data.datatourisme.fr/6e9ed747-5be0-3810-b1cd-1a598b1a9c28",
          "schema:closes": "18:00:00",
          "schema:dayOfWeek": [
            {
              "@id": "schema:Saturday",
              "@type": [
                "schema:DayOfWeek"
              ],
              "rdfs:label": {
                "de": [
                  "Samstag"
                ],
                "pt": [
                  "Sábado"
                ],
                "en": [
                  "Saturday"
                ],
                "it": [
                  "Sabato"
                ],
                "fr": [
                  "Samedi"
                ],
                "nl": [
                  "Zaterdag"
                ],
                "es": [
                  "Sábado"
                ]
              }
            }
          ],
          "schema:opens": "09:00:00",
          "schema:validFrom": "2024-01-01T09:00:00",
          "schema:validThrough": "2024-12-31T18:00:00",
          "@type": [
            "schema:OpeningHoursSpecification"
          ]
        },
        {
          "@id": "https://data.datatourisme.fr/75c528c5-0b11-3b2b-8a16-213caad4ba50",
          "schema:closes": "18:00:00",
          "schema:dayOfWeek": [
            {
              "@id": "schema:Friday",
              "@type": [
                "schema:DayOfWeek"
              ],
              "rdfs:label": {
                "de": [
                  "Freitag"
                ],
                "pt": [
                  "Sexta-feira"
                ],
                "en": [
                  "Friday"
                ],
                "it": [
                  "Venerdì"
                ],
                "fr": [
                  "Vendredi"
                ],
                "nl": [
                  "Vrijdag"
                ],
                "es": [
                  "Viernes"
                ]
              }
            }
          ],
          "schema:opens": "09:00:00",
          "schema:validFrom": "2024-01-01T09:00:00",
          "schema:validThrough": "2024-12-31T18:00:00",
          "@type": [
            "schema:OpeningHoursSpecification"
          ]
        },
        {
          "@id": "https://data.datatourisme.fr/c32354cb-3332-38a1-98ab-3228d78318b8",
          "schema:closes": "14:00:00",
          "schema:dayOfWeek": [
            {
              "@id": "schema:Sunday",
              "@type": [
                "schema:DayOfWeek"
              ],
              "rdfs:label": {
                "de": [
                  "Sonntag"
                ],
                "pt": [
                  "Domingo"
                ],
                "en": [
                  "Sunday"
                ],
                "it": [
                  "Domenica"
                ],
                "fr": [
                  "Dimanche"
                ],
                "nl": [
                  "Zondag"
                ],
                "es": [
                  "Domingo"
                ]
              }
            }
          ],
          "schema:opens": "09:00:00",
          "schema:validFrom": "2024-01-01T09:00:00",
          "schema:validThrough": "2024-12-31T14:00:00",
          "@type": [
            "schema:OpeningHoursSpecification"
          ]
        },
        {
          "@id": "https://data.datatourisme.fr/c4c29dbf-b84f-326a-afda-2f44a06f0541",
          "schema:closes": "18:00:00",
          "schema:dayOfWeek": [
            {
              "@id": "schema:Thursday",
              "@type": [
                "schema:DayOfWeek"
              ],
              "rdfs:label": {
                "de": [
                  "Donnerstag"
                ],
                "pt": [
                  "Quinta-feira"
                ],
                "en": [
                  "Thursday"
                ],
                "it": [
                  "Giovedì"
                ],
                "fr": [
                  "Jeudi"
                ],
                "es": [
                  "Jueves"
                ],
                "nl": [
                  "Donderdag"
                ]
              }
            }
          ],
          "schema:opens": "09:00:00",
          "schema:validFrom": "2024-01-01T09:00:00",
          "schema:validThrough": "2024-12-31T18:00:00",
          "@type": [
            "schema:OpeningHoursSpecification"
          ]
        },
        {
          "@id": "https://data.datatourisme.fr/d1207f53-f19a-3f3d-bf63-a9f21c49512a",
          "schema:closes": "18:00:00",
          "schema:dayOfWeek": [
            {
              "@id": "schema:Wednesday",
              "@type": [
                "schema:DayOfWeek"
              ],
              "rdfs:label": {
                "de": [
                  "Mittwoch"
                ],
                "pt": [
                  "Quarta-feira"
                ],
                "en": [
                  "Wednesday"
                ],
                "it": [
                  "Mercoledì"
                ],
                "fr": [
                  "Mercredi"
                ],
                "nl": [
                  "Woensdag"
                ],
                "es": [
                  "Miércoles"
                ]
              }
            }
          ],
          "schema:opens": "09:00:00",
          "schema:validFrom": "2024-01-01T09:00:00",
          "schema:validThrough": "2024-12-31T18:00:00",
          "@type": [
            "schema:OpeningHoursSpecification"
          ]
        }
      ],
      "@type": [
        "schema:Place",
        "Place"
      ]
    }
  ],
  "isOwnedBy": [
    {
      "@id": "https://data.datatourisme.fr/e130700b-a65b-31fb-a5be-1139b111f4d9",
      "schema:legalName": "Poney Club Bucey",
      "@type": [
        "schema:Organization",
        "foaf:Agent",
        "Agent"
      ]
    }
  ],
  "lastUpdate": "2024-01-10",
  "lastUpdateDatatourisme": "2025-05-23T07:48:52.351Z"
}