{
  "@id": "https://data.datatourisme.fr/49/0caf12c9-edb9-38cb-8b34-5534bceff413",
  "dc:identifier": "HPAKIRCAMPINGLESERPOLIN",
  "@type": [
    "schema:Accommodation",
    "schema:LodgingBusiness",
    "Accommodation",
    "Camping",
    "CampingAndCaravanning",
    "PlaceOfInterest",
    "PointOfInterest"
  ],
  "rdfs:comment": {
    "de": [
      "Der Campingplatz Le Serpolin befindet sich in einer wunderschönen und ruhigen Umgebung, die ideal zum Entspannen ist."
    ],
    "en": [
      "Camping Le Serpolin is set in beautiful, tranquil surroundings, ideal for relaxation."
    ],
    "it": [
      "Il Camping Le Serpolin si trova in un ambiente magnifico e tranquillo, ideale per il relax."
    ],
    "fr": [
      "Le Camping Le Serpolin est situé dans un cadre magnifique et tranquille, idéal pour la détente."
    ],
    "es": [
      "El camping Le Serpolin está situado en un entorno magnífico y tranquilo, ideal para relajarse."
    ],
    "nl": [
      "Camping Le Serpolin ligt in een prachtige, rustige omgeving, ideaal om te ontspannen."
    ]
  },
  "rdfs:label": {
    "fr": [
      "Camping Le Serpolin"
    ]
  },
  "availableLanguage": [
    "en",
    "fr"
  ],
  "creationDate": "2017-10-27",
  "hasBeenCreatedBy": {
    "@id": "https://data.datatourisme.fr/5083a8e7-1c14-37e3-a434-a4cb6ef3cdb2",
    "schema:email": [
      "info-accueil@ot-cholet.fr"
    ],
    "schema:legalName": "Office de tourisme du Choletais",
    "@type": [
      "schema:Organization",
      "foaf:Agent",
      "Agent"
    ]
  },
  "hasBeenPublishedBy": [
    {
      "@id": "https://data.datatourisme.fr/e014813e-a168-3a77-b882-6ad07382274d",
      "schema:email": [
        "contact@anjou-tourisme.com"
      ],
      "schema:legalName": "Anjou tourime",
      "@type": [
        "schema:Organization",
        "foaf:Agent",
        "Agent"
      ],
      "rdfs:comment": {
        "de": [
          "Anjou tourisme & attractivité, die Tourismusagentur des Departements Anjou, ist eine öffentliche Interessenvereinigung, deren Aufgabe es ist, gemeinsam mit den lokalen Wirtschaftsakteuren zur Strategie der touristischen Entwicklung des Anjou beizutragen."
        ],
        "en": [
          "Anjou tourisme & attractivité, Anjou?s departmental tourism agency, is a Public Interest Group whose mission is to contribute to Anjou?s tourism development strategy with local economic players."
        ],
        "it": [
          "Anjou tourisme & attractivité, l'agenzia turistica dipartimentale dell'Anjou, è un Gruppo di interesse pubblico la cui missione è contribuire alla strategia di sviluppo turistico dell'Anjou con gli attori economici locali."
        ],
        "fr": [
          "Anjou tourisme & attractivité, Agence départementale du tourisme de l’Anjou, est un Groupement d’Intérêt Public qui a pour mission de contribuer à la stratégie de développement touristique de l’Anjou avec les acteurs économiques locaux."
        ],
        "nl": [
          "Anjou tourisme & attractivité, het departementale agentschap voor toerisme van Anjou, is een groep van openbaar belang die als missie heeft om bij te dragen aan de strategie voor de ontwikkeling van toerisme in Anjou, in samenwerking met lokale economische spelers."
        ],
        "es": [
          "Anjou tourisme & attractivité, agencia departamental de turismo de Anjou, es una Agrupación de Interés Público cuya misión es contribuir a la estrategia de desarrollo turístico de Anjou con los agentes económicos locales."
        ]
      },
      "foaf:homepage": [
        "https://pro.anjou-tourisme.com/"
      ],
      "hasTranslatedProperty": [
        {
          "@id": "https://data.datatourisme.fr/405fbffd-c3f5-3985-b724-2ddb4e4777a6",
          "dc:contributor": [
            "https://api.deepl.com/v2/translate"
          ],
          "rdf:language": [
            "nl"
          ],
          "rdf:predicate": [
            {
              "@id": "rdfs:comment"
            }
          ]
        },
        {
          "@id": "https://data.datatourisme.fr/44245f46-1b26-3ec3-bf61-b80fd771780e",
          "dc:contributor": [
            "https://api.deepl.com/v2/translate"
          ],
          "rdf:language": [
            "de"
          ],
          "rdf:predicate": [
            {
              "@id": "rdfs:comment"
            }
          ]
        },
        {
          "@id": "https://data.datatourisme.fr/509a9547-3e61-3774-bcbc-2984f955da10",
          "dc:contributor": [
            "https://api.deepl.com/v2/translate"
          ],
          "rdf:language": [
            "es"
          ],
          "rdf:predicate": [
            {
              "@id": "rdfs:comment"
            }
          ]
        },
        {
          "@id": "https://data.datatourisme.fr/778b682b-e45f-3c3c-a679-b23bf53e96fa",
          "dc:contributor": [
            "https://api.deepl.com/v2/translate"
          ],
          "rdf:language": [
            "en"
          ],
          "rdf:predicate": [
            {
              "@id": "rdfs:comment"
            }
          ]
        },
        {
          "@id": "https://data.datatourisme.fr/af44157d-54e9-399e-9254-6dd00407160a",
          "dc:contributor": [
            "https://api.deepl.com/v2/translate"
          ],
          "rdf:language": [
            "it"
          ],
          "rdf:predicate": [
            {
              "@id": "rdfs:comment"
            }
          ]
        }
      ]
    }
  ],
  "hasContact": [
    {
      "@id": "https://data.datatourisme.fr/b616ae74-e530-3e19-8f13-b8d8711f6984",
      "schema:email": [
        "campingleserpolin@gmail.com"
      ],
      "schema:telephone": [
        "+33 2 41 03 22 72",
        "+33 7 86 97 84 13"
      ],
      "@type": [
        "foaf:Agent",
        "Agent"
      ],
      "foaf:homepage": [
        "http://www.campingleserpolin.org/"
      ]
    }
  ],
  "hasDescription": [
    {
      "@id": "https://data.datatourisme.fr/302139f6-22b0-3d13-a7fa-2ef36201d6cc",
      "dc:description": {
        "de": [
          "Ein 5 Hektar großes, landschaftlich gestaltetes Gelände bietet 16 große Stellplätze mit Stromanschluss (10 Ampere), davon 6 erschlossene Stellplätze mit direktem Zugang zu Trinkwasser/Dusche und Grauwasser-Abwasserentsorgung.\nGenießen Sie Ihren Aufenthalt mit den Aktivitäten auf dem Campingplatz (Angeln, beheiztes Schwimmbad, Bouleplatz und Spielplätze für Groß und Klein), aber auch mit Ausflügen in die Region und zu den umliegenden Sehenswürdigkeiten: Weinberge des Haut-Layon, Parc Oriental de Maulévrier, Bioparc Doué-la-Fontaine, Puy du Fou, etc.\nAuf dem gesamten Campingplatz gibt es eine kostenlose Wi-Fi-Verbindung.\nDas ganze Jahr über werden an jedem ersten und dritten Freitag im Monat Fish&Chips-Abende veranstaltet."
        ],
        "en": [
          "A landscaped 5-hectare site offers 16 large pitches equipped with electrical hook-ups (10 amps), including 6 serviced pitches with direct access to drinking water/shower and grey water drainage.\nMake the most of your stay with the campsite's activities (fishing, heated swimming pool, pétanque court and playgrounds for young and old), as well as by visiting the surrounding region and sites: Haut-Layon vineyards, Parc Oriental de Maulévrier, Doué-la-Fontaine Biopark, Puy du Fou, etc.\nFree Wi-Fi access is available throughout the campsite.\nA communal barbecue is available to holidaymakers, and Fish&Chips evenings are held all year round, on the first and third Fridays of each month."
        ],
        "it": [
          "Un sito paesaggistico di 5 ettari offre 16 ampie piazzole dotate di allaccio elettrico (10 ampere), di cui 6 piazzole servite con accesso diretto all'acqua potabile/doccia e scarico delle acque grigie.\nApprofittate del vostro soggiorno con le attività del campeggio (pesca, piscina riscaldata, campo da bocce e aree gioco per grandi e piccini) e anche visitando la regione e i siti circostanti: vigneti dell'Haut-Layon, Parco Orientale del Maulévrier, Bioparco di Doué-la-Fontaine, Puy du Fou, ecc.\nLa connessione Wi-Fi è disponibile gratuitamente in tutto il campeggio.\nUn barbecue comune è a disposizione dei vacanzieri e le serate Fish&Chips si tengono durante tutto l'anno il primo e il terzo venerdì di ogni mese."
        ],
        "fr": [
          "Un terrain paysagé de 5 hectares propose 16 grands emplacements équipés de branchements électriques (10 ampères), dont 6 emplacements viabilisés avec accès direct à l'eau potable/douche et à l'évacuation des eaux grises usées.\nProfitez de votre séjour avec les activités du camping (pêche, piscine chauffée, terrain de pétanque et aires de jeux pour petits et grands) mais aussi en visitant la région et les sites alentours : vignoble du Haut-Layon, Parc Oriental de Maulévrier, Bioparc de Doué-la -Fontaine, Puy du Fou, etc.\nUne connexion Wi-Fi gratuite est disponible dans tout le camping.\nUn barbecue commun est mis à disposition des vacanciers, et des soirées Fish&Chips sont proposées toute l'année, les premiers et troisièmes vendredis de chaque mois."
        ],
        "es": [
          "Un terreno ajardinado de 5 hectáreas ofrece 16 amplias parcelas equipadas con conexión eléctrica (10 amperios), 6 de ellas con servicios, acceso directo al agua potable/ducha y evacuación de aguas grises.\nDisfrute al máximo de su estancia con las actividades del camping (pesca, piscina climatizada, campo de petanca y zonas de juego para grandes y pequeños) y también visitando la región y los lugares de los alrededores: viñedos de Haut-Layon, Parque Oriental de Maulévrier, Bioparque de Doué-la-Fontaine, Puy du Fou, etc.\nHay conexión Wi-Fi gratuita en todo el camping.\nLos veraneantes tienen a su disposición una barbacoa común y durante todo el año, el primer y tercer viernes de cada mes, se organizan veladas Fish&Chips."
        ],
        "nl": [
          "Op een aangelegd terrein van 5 hectare vind je 16 ruime staanplaatsen met elektriciteit (10 ampère), waarvan 6 serviceplaatsen met directe toegang tot drinkwater/douche en afvoer van grijs water.\nGeniet van je verblijf met de activiteiten op de camping (vissen, verwarmd zwembad, petanqueterrein en speeltuinen voor groot en klein), maar ook van een bezoek aan de streek en de omliggende plaatsen: de wijngaarden van Haut-Layon, het Oriëntaalse Park van Maulévrier, het Biopark van Doué-la-Fontaine, Puy du Fou, enz.\nOp de hele camping is gratis wifi beschikbaar.\nEr is een gemeenschappelijke barbecue voor de vakantiegangers en er worden het hele jaar door Fish&Chips-avonden georganiseerd op de eerste en derde vrijdag van elke maand."
        ]
      },
      "@type": [
        "Description"
      ],
      "hasTranslatedProperty": [
        {
          "@id": "https://data.datatourisme.fr/0a278236-df1f-3c61-bc0c-985d1a184e95",
          "dc:contributor": [
            "https://api.deepl.com/v2/translate"
          ],
          "rdf:language": [
            "nl"
          ],
          "rdf:predicate": [
            "shortDescription"
          ]
        },
        {
          "@id": "https://data.datatourisme.fr/1168aa5e-848b-3111-8e4a-48857d677a15",
          "dc:contributor": [
            "https://api.deepl.com/v2/translate"
          ],
          "rdf:language": [
            "nl"
          ],
          "rdf:predicate": [
            {
              "@id": "dc:description"
            }
          ]
        },
        {
          "@id": "https://data.datatourisme.fr/29838ba0-0e8c-3775-bfcb-5d1e93a8dca4",
          "dc:contributor": [
            "https://api.deepl.com/v2/translate"
          ],
          "rdf:language": [
            "de"
          ],
          "rdf:predicate": [
            {
              "@id": "dc:description"
            }
          ]
        },
        {
          "@id": "https://data.datatourisme.fr/2ea9871e-9b97-312a-ba94-97b808c73553",
          "dc:contributor": [
            "https://api.deepl.com/v2/translate"
          ],
          "rdf:language": [
            "es"
          ],
          "rdf:predicate": [
            {
              "@id": "dc:description"
            }
          ]
        },
        {
          "@id": "https://data.datatourisme.fr/4773f8d7-56f0-35df-8f30-0a531c7cfeef",
          "dc:contributor": [
            "https://api.deepl.com/v2/translate"
          ],
          "rdf:language": [
            "en"
          ],
          "rdf:predicate": [
            {
              "@id": "dc:description"
            }
          ]
        },
        {
          "@id": "https://data.datatourisme.fr/4e57c68a-f3c5-3b70-86bc-a9485cb5b254",
          "dc:contributor": [
            "https://api.deepl.com/v2/translate"
          ],
          "rdf:language": [
            "de"
          ],
          "rdf:predicate": [
            "shortDescription"
          ]
        },
        {
          "@id": "https://data.datatourisme.fr/76d5ddd0-789b-31f8-9b8e-207596e81ba8",
          "dc:contributor": [
            "https://api.deepl.com/v2/translate"
          ],
          "rdf:language": [
            "es"
          ],
          "rdf:predicate": [
            "shortDescription"
          ]
        },
        {
          "@id": "https://data.datatourisme.fr/8160582e-eb78-3329-96d7-ea96c5686257",
          "dc:contributor": [
            "https://api.deepl.com/v2/translate"
          ],
          "rdf:language": [
            "it"
          ],
          "rdf:predicate": [
            "shortDescription"
          ]
        },
        {
          "@id": "https://data.datatourisme.fr/868ca6e2-e34c-35c0-aa70-a7c5d7653c6e",
          "dc:contributor": [
            "https://api.deepl.com/v2/translate"
          ],
          "rdf:language": [
            "en"
          ],
          "rdf:predicate": [
            "shortDescription"
          ]
        },
        {
          "@id": "https://data.datatourisme.fr/bc42b4df-17c8-371d-a489-81aecb298be5",
          "dc:contributor": [
            "https://api.deepl.com/v2/translate"
          ],
          "rdf:language": [
            "it"
          ],
          "rdf:predicate": [
            {
              "@id": "dc:description"
            }
          ]
        }
      ],
      "shortDescription": {
        "de": [
          "Der Campingplatz Le Serpolin befindet sich in einer wunderschönen und ruhigen Umgebung, die ideal zum Entspannen ist."
        ],
        "en": [
          "Camping Le Serpolin is set in beautiful, tranquil surroundings, ideal for relaxation."
        ],
        "it": [
          "Il Camping Le Serpolin si trova in un ambiente magnifico e tranquillo, ideale per il relax."
        ],
        "fr": [
          "Le Camping Le Serpolin est situé dans un cadre magnifique et tranquille, idéal pour la détente."
        ],
        "es": [
          "El camping Le Serpolin está situado en un entorno magnífico y tranquilo, ideal para relajarse."
        ],
        "nl": [
          "Camping Le Serpolin ligt in een prachtige, rustige omgeving, ideaal om te ontspannen."
        ]
      }
    }
  ],
  "hasFeature": [
    {
      "@id": "https://data.datatourisme.fr/4f533e68-e395-38ec-84c8-63df3537c904",
      "@type": [
        "schema:PropertyValue",
        "FeatureSpecification"
      ],
      "features": [
        {
          "@id": "kb:SwimmingPool",
          "@type": [
            "CommonAmenity"
          ],
          "rdfs:label": {
            "de": [
              "Pool"
            ],
            "pt": [
              "Piscina"
            ],
            "en": [
              "Swimming pool"
            ],
            "it": [
              "Piscina"
            ],
            "fr": [
              "Piscine"
            ],
            "nl": [
              "Zwembad"
            ],
            "es": [
              "Piscina"
            ]
          }
        }
      ],
      "hasFloorSize": {
        "@id": "https://data.datatourisme.fr/594bee9e-fea2-3a91-a1bf-d15acea9e590",
        "schema:unitText": [
          "m²"
        ],
        "@type": [
          "schema:QuantitativeValue"
        ]
      }
    },
    {
      "@id": "https://data.datatourisme.fr/c571a292-96cd-314f-b9fb-5c93c8d149f2",
      "schema:value": "16",
      "@type": [
        "schema:PropertyValue",
        "FeatureSpecification"
      ],
      "features": [
        {
          "@id": "kb:BarePitch",
          "@type": [
            "AccommodationPricingOffer",
            "CampingAndCaravanningAmenity"
          ],
          "rdfs:label": {
            "de": [
              "Stellplatz"
            ],
            "pt": [
              "Local vazio"
            ],
            "en": [
              "Bare pitch"
            ],
            "it": [
              "Solo piazzola"
            ],
            "fr": [
              "Emplacement nu"
            ],
            "es": [
              "Terreno vacío"
            ],
            "nl": [
              "Kale standplaats"
            ]
          }
        },
        {
          "@id": "kb:Pitch",
          "@type": [
            "AccommodationPricingOffer",
            "CampingAndCaravanningAmenity"
          ],
          "rdfs:label": {
            "de": [
              "Lage"
            ],
            "pt": [
              "Local"
            ],
            "en": [
              "Pitch"
            ],
            "it": [
              "Piazzola"
            ],
            "fr": [
              "Emplacement"
            ],
            "nl": [
              "Plaats"
            ],
            "es": [
              "Parcela"
            ]
          }
        }
      ],
      "hasFloorSize": {
        "@id": "https://data.datatourisme.fr/594bee9e-fea2-3a91-a1bf-d15acea9e590",
        "schema:unitText": [
          "m²"
        ],
        "@type": [
          "schema:QuantitativeValue"
        ]
      }
    }
  ],
  "hasTranslatedProperty": [
    {
      "@id": "https://data.datatourisme.fr/2069ac2f-107c-31de-abf6-9ab0671e2f34",
      "dc:contributor": [
        "https://api.deepl.com/v2/translate"
      ],
      "rdf:language": [
        "es"
      ],
      "rdf:predicate": [
        {
          "@id": "rdfs:comment"
        }
      ]
    },
    {
      "@id": "https://data.datatourisme.fr/300c48f5-9af9-3233-95ac-127c282cc12d",
      "dc:contributor": [
        "https://api.deepl.com/v2/translate"
      ],
      "rdf:language": [
        "de"
      ],
      "rdf:predicate": [
        {
          "@id": "rdfs:comment"
        }
      ]
    },
    {
      "@id": "https://data.datatourisme.fr/7e33791d-dcc5-398b-963f-26e1bdd569e1",
      "dc:contributor": [
        "https://api.deepl.com/v2/translate"
      ],
      "rdf:language": [
        "it"
      ],
      "rdf:predicate": [
        {
          "@id": "rdfs:comment"
        }
      ]
    },
    {
      "@id": "https://data.datatourisme.fr/ca8061d0-1bfa-33af-bf44-fba4c54fe271",
      "dc:contributor": [
        "https://api.deepl.com/v2/translate"
      ],
      "rdf:language": [
        "en"
      ],
      "rdf:predicate": [
        {
          "@id": "rdfs:comment"
        }
      ]
    },
    {
      "@id": "https://data.datatourisme.fr/ea7e3d75-775c-3416-bd6c-5f53e2f59930",
      "dc:contributor": [
        "https://api.deepl.com/v2/translate"
      ],
      "rdf:language": [
        "nl"
      ],
      "rdf:predicate": [
        {
          "@id": "rdfs:comment"
        }
      ]
    }
  ],
  "isLocatedAt": [
    {
      "@id": "https://data.datatourisme.fr/6d239016-a948-35a6-b3d6-9dc053dea327",
      "schema:address": [
        {
          "@id": "https://data.datatourisme.fr/61121001-2a10-30e4-a62b-77790b4421a3",
          "schema:addressLocality": "Cléré-sur-Layon",
          "schema:postalCode": "49560",
          "schema:streetAddress": [
            "Lieu dit Le Serpolin"
          ],
          "@type": [
            "schema:PostalAddress",
            "PostalAddress"
          ],
          "hasAddressCity": {
            "@id": "kb:49102",
            "@type": [
              "City"
            ],
            "rdfs:label": {
              "de": [
                "Cléré-sur-Layon"
              ],
              "pt": [
                "Cléré-sur-Layon"
              ],
              "en": [
                "Cléré-sur-Layon"
              ],
              "it": [
                "Cléré-sur-Layon"
              ],
              "fr": [
                "Cléré-sur-Layon"
              ],
              "nl": [
                "Cléré-sur-Layon"
              ],
              "es": [
                "Cléré-sur-Layon"
              ]
            },
            "insee": "49102",
            "isPartOfDepartment": {
              "@id": "kb:France5249",
              "@type": [
                "Department"
              ],
              "rdfs:label": {
                "de": [
                  "Maine-et-Loire"
                ],
                "pt": [
                  "Maine-et-Loire"
                ],
                "en": [
                  "Maine-et-Loire"
                ],
                "it": [
                  "Maine-et-Loire"
                ],
                "fr": [
                  "Maine-et-Loire"
                ],
                "nl": [
                  "Maine-et-Loire"
                ],
                "es": [
                  "Maine-et-Loire"
                ]
              },
              "insee": "49",
              "isPartOfRegion": {
                "@id": "kb:France52",
                "@type": [
                  "Region"
                ],
                "rdfs:label": {
                  "de": [
                    "Pays de la Loire"
                  ],
                  "pt": [
                    "Pays de la Loire"
                  ],
                  "en": [
                    "Pays de la Loire"
                  ],
                  "it": [
                    "Pays de la Loire"
                  ],
                  "fr": [
                    "Pays de la Loire"
                  ],
                  "nl": [
                    "Pays de la Loire"
                  ],
                  "es": [
                    "Pays de la Loire"
                  ]
                },
                "insee": "52",
                "isPartOfCountry": {
                  "@id": "kb:France",
                  "@type": [
                    "schema:Country"
                  ],
                  "rdfs:label": {
                    "de": [
                      "France",
                      "Frankreich"
                    ],
                    "pt": [
                      "França",
                      "France"
                    ],
                    "en": [
                      "France"
                    ],
                    "it": [
                      "France",
                      "Francia"
                    ],
                    "fr": [
                      "France"
                    ],
                    "nl": [
                      "France",
                      "Frankrijk"
                    ],
                    "es": [
                      "France",
                      "Francia"
                    ]
                  }
                }
              }
            }
          }
        }
      ],
      "schema:geo": {
        "@id": "https://data.datatourisme.fr/68cc27c7-2b6d-3b63-ba8c-8bf56a816a30",
        "schema:latitude": "47.07351",
        "schema:longitude": "-0.40905",
        "@type": [
          "schema:GeoCoordinates"
        ]
      },
      "@type": [
        "schema:Place",
        "Place"
      ]
    }
  ],
  "lastUpdate": "2025-08-02",
  "lastUpdateDatatourisme": "2025-08-03T00:24:51.857Z",
  "offers": [
    {
      "@id": "https://data.datatourisme.fr/ef06a3d2-146f-3cac-b044-d55ad2d6a22b",
      "schema:acceptedPaymentMethod": [
        {
          "@id": "kb:Cash",
          "@type": [
            "schema:PaymentMethod"
          ],
          "rdfs:label": {
            "de": [
              "Art"
            ],
            "pt": [
              "Espécie"
            ],
            "en": [
              "Cash"
            ],
            "it": [
              "Contanti"
            ],
            "fr": [
              "Espèce"
            ],
            "es": [
              "Especie"
            ],
            "nl": [
              "Contant"
            ]
          }
        },
        {
          "@id": "kb:Check",
          "@type": [
            "schema:PaymentMethod"
          ],
          "rdfs:label": {
            "de": [
              "Scheck"
            ],
            "pt": [
              "Cheque"
            ],
            "en": [
              "Check"
            ],
            "it": [
              "Assegno"
            ],
            "fr": [
              "Chèque"
            ],
            "nl": [
              "Cheque"
            ],
            "es": [
              "Cheque"
            ]
          }
        },
        {
          "@id": "kb:Transfers",
          "@type": [
            "schema:PaymentMethod"
          ],
          "rdfs:label": {
            "de": [
              "Überweisungen"
            ],
            "pt": [
              "Transferências"
            ],
            "en": [
              "Transfers"
            ],
            "it": [
              "Bonifici"
            ],
            "fr": [
              "Virements"
            ],
            "es": [
              "Transferencias"
            ],
            "nl": [
              "Overschrijvingen"
            ]
          }
        }
      ],
      "@type": [
        "schema:Offer",
        "Offer"
      ]
    }
  ]
}