{
  "@id": "https://data.datatourisme.fr/56/05c3b4f9-1edb-3b23-aa27-c190d3f7a999",
  "dc:identifier": "FMALAR066V52R5ES",
  "schema:endDate": [
    "2025-08-05"
  ],
  "schema:startDate": [
    "2025-08-05"
  ],
  "@type": [
    "schema:Event",
    "schema:SportsEvent",
    "EntertainmentAndEvent",
    "PointOfInterest",
    "Rambling",
    "SportsEvent"
  ],
  "rdfs:comment": {
    "de": [
      "Wanderung mit dem elektrischen Mountainbike. Geschichte und Kulturerbe des Capcir, Treffen mit Einwohnern und Erzeugern, Verkostung lokaler Produkte. Obligatorische Anmeldung bei Eco Bike, 07.87.71.64.72 Mountainbike, Helm und Betreuung inbegriffen. Kostenpflichtige Ausfahrt (65 e..."
    ],
    "en": [
      "Electric mountain bike tour. History and heritage of Capcir, meet local people and producers, taste local products. Registration required with Eco Bike, 07.87.71.64.72 VTTAE, helmet and supervision included. Paying excursion (65 e..."
    ],
    "it": [
      "Giro in mountain bike elettrica. Storia e patrimonio del Capcir, incontro con persone e produttori locali, degustazione di prodotti locali. È necessario iscriversi presso Eco Bike, 07.87.71.64.72 VTTAE, casco e supervisione inclusi. Quota di partecipazione (65 euro a persona)."
    ],
    "fr": [
      "Randonnée VTT électrique. Histoire et patrimoine du Capcir, rencontre d'habitant et de producteurs, dégustation de produits locaux. Inscriptions obligatoires auprès d'Eco Bike, 07.87.71.64.72 VTTAE, casque et encadrement compris. Sortie payante (65 e..."
    ],
    "es": [
      "Paseo en bicicleta eléctrica de montaña. Historia y patrimonio del Capcir, encuentro con la población y los productores locales, degustación de productos locales. Hay que inscribirse en Eco Bike, 07.87.71.64.72 VTTAE, casco y supervisión incluidos. Tarifa de pago (65 euros por persona)."
    ],
    "nl": [
      "Elektrische mountainbiketocht. Geschiedenis en erfgoed van de Capcir, ontmoet lokale mensen en producenten, proef lokale producten. Aanmelden bij Eco Bike, 07.87.71.64.72 VTTAE, helm en begeleiding inbegrepen. Kosten te betalen (65 euro per persoon)."
    ]
  },
  "rdfs:label": {
    "fr": [
      "VTT HISTOIRE DU PATRIMOINE"
    ]
  },
  "availableLanguage": [
    "en",
    "es",
    "fr"
  ],
  "creationDate": "2025-06-06",
  "hasBeenCreatedBy": {
    "@id": "https://data.datatourisme.fr/5e0af707-d18c-3d82-b53f-7c5bad2ef44c",
    "schema:legalName": "LES ANGLES LE VILLAGE STATION",
    "@type": [
      "schema:Organization",
      "foaf:Agent",
      "Agent"
    ]
  },
  "hasBeenPublishedBy": [
    {
      "@id": "https://data.datatourisme.fr/dd99d1ce-e7fe-3bb7-8926-53ae14d62fd0",
      "schema:address": [
        {
          "@id": "https://data.datatourisme.fr/0987cee9-9af8-3164-818d-145a31865e17",
          "schema:addressLocality": "Perpignan",
          "schema:postalCode": "66005",
          "schema:streetAddress": [
            "2 Bd des Pyrénées"
          ],
          "@type": [
            "schema:PostalAddress",
            "PostalAddress"
          ],
          "cedex": "CS 80540",
          "hasAddressCity": {
            "@id": "kb:66136",
            "@type": [
              "City"
            ],
            "rdfs:label": {
              "de": [
                "Perpignan"
              ],
              "pt": [
                "Perpignan"
              ],
              "en": [
                "Perpignan"
              ],
              "it": [
                "Perpignan"
              ],
              "fr": [
                "Perpignan"
              ],
              "nl": [
                "Perpignan"
              ],
              "es": [
                "Perpignan"
              ]
            },
            "insee": "66136",
            "isPartOfDepartment": {
              "@id": "kb:France7666",
              "@type": [
                "Department"
              ],
              "rdfs:label": {
                "de": [
                  "Pyrénées-Orientales"
                ],
                "pt": [
                  "Pyrénées-Orientales"
                ],
                "en": [
                  "Pyrénées-Orientales"
                ],
                "it": [
                  "Pyrénées-Orientales"
                ],
                "fr": [
                  "Pyrénées-Orientales"
                ],
                "nl": [
                  "Pyrénées-Orientales"
                ],
                "es": [
                  "Pyrénées-Orientales"
                ]
              },
              "insee": "66",
              "isPartOfRegion": {
                "@id": "kb:France76",
                "@type": [
                  "Region"
                ],
                "rdfs:label": {
                  "de": [
                    "Occitanie"
                  ],
                  "pt": [
                    "Occitanie"
                  ],
                  "en": [
                    "Occitanie"
                  ],
                  "it": [
                    "Occitanie"
                  ],
                  "fr": [
                    "Occitanie"
                  ],
                  "nl": [
                    "Occitanie"
                  ],
                  "es": [
                    "Occitanie"
                  ]
                },
                "insee": "76",
                "isPartOfCountry": {
                  "@id": "kb:France",
                  "@type": [
                    "schema:Country"
                  ],
                  "rdfs:label": {
                    "de": [
                      "France",
                      "Frankreich"
                    ],
                    "pt": [
                      "França",
                      "France"
                    ],
                    "en": [
                      "France"
                    ],
                    "it": [
                      "France",
                      "Francia"
                    ],
                    "fr": [
                      "France"
                    ],
                    "nl": [
                      "France",
                      "Frankrijk"
                    ],
                    "es": [
                      "France",
                      "Francia"
                    ]
                  }
                }
              }
            }
          }
        }
      ],
      "schema:legalName": "Pyrénées-Orientales Tourisme",
      "@type": [
        "schema:Organization",
        "foaf:Agent",
        "Agent"
      ],
      "foaf:homepage": [
        "https://www.tourisme-pyreneesorientales.com/"
      ]
    }
  ],
  "hasContact": [
    {
      "@id": "https://data.datatourisme.fr/fe4f11d9-8e3b-3440-8303-81e0ebb0ecd6",
      "schema:address": [
        {
          "@id": "https://data.datatourisme.fr/10f33a6e-ac7e-36d5-a63d-843ff609543e",
          "schema:addressLocality": "Les Angles",
          "schema:postalCode": "66210",
          "@type": [
            "schema:PostalAddress",
            "PostalAddress"
          ],
          "hasAddressCity": {
            "@id": "kb:66004",
            "@type": [
              "City"
            ],
            "rdfs:label": {
              "de": [
                "Les Angles"
              ],
              "pt": [
                "Les Angles"
              ],
              "en": [
                "Les Angles"
              ],
              "it": [
                "Les Angles"
              ],
              "fr": [
                "Les Angles"
              ],
              "nl": [
                "Les Angles"
              ],
              "es": [
                "Les Angles"
              ]
            },
            "insee": "66004",
            "isPartOfDepartment": {
              "@id": "kb:France7666",
              "@type": [
                "Department"
              ],
              "rdfs:label": {
                "de": [
                  "Pyrénées-Orientales"
                ],
                "pt": [
                  "Pyrénées-Orientales"
                ],
                "en": [
                  "Pyrénées-Orientales"
                ],
                "it": [
                  "Pyrénées-Orientales"
                ],
                "fr": [
                  "Pyrénées-Orientales"
                ],
                "nl": [
                  "Pyrénées-Orientales"
                ],
                "es": [
                  "Pyrénées-Orientales"
                ]
              },
              "insee": "66",
              "isPartOfRegion": {
                "@id": "kb:France76",
                "@type": [
                  "Region"
                ],
                "rdfs:label": {
                  "de": [
                    "Occitanie"
                  ],
                  "pt": [
                    "Occitanie"
                  ],
                  "en": [
                    "Occitanie"
                  ],
                  "it": [
                    "Occitanie"
                  ],
                  "fr": [
                    "Occitanie"
                  ],
                  "nl": [
                    "Occitanie"
                  ],
                  "es": [
                    "Occitanie"
                  ]
                },
                "insee": "76",
                "isPartOfCountry": {
                  "@id": "kb:France",
                  "@type": [
                    "schema:Country"
                  ],
                  "rdfs:label": {
                    "de": [
                      "France",
                      "Frankreich"
                    ],
                    "pt": [
                      "França",
                      "France"
                    ],
                    "en": [
                      "France"
                    ],
                    "it": [
                      "France",
                      "Francia"
                    ],
                    "fr": [
                      "France"
                    ],
                    "nl": [
                      "France",
                      "Frankrijk"
                    ],
                    "es": [
                      "France",
                      "Francia"
                    ]
                  }
                }
              }
            }
          }
        }
      ],
      "schema:legalName": "VTT HISTOIRE DU PATRIMOINE",
      "schema:telephone": [
        "+33 7 87 71 64 72"
      ],
      "@type": [
        "schema:Organization",
        "foaf:Agent",
        "Agent"
      ]
    }
  ],
  "hasDescription": [
    {
      "@id": "https://data.datatourisme.fr/9ad4a0fc-ee29-33ff-b249-f3d52904a8eb",
      "@type": [
        "Description"
      ],
      "hasTranslatedProperty": [
        {
          "@id": "https://data.datatourisme.fr/0a74a261-daac-3a3c-a7b1-8589b788827c",
          "dc:contributor": [
            "https://api.deepl.com/v2/translate"
          ],
          "rdf:language": [
            "de"
          ],
          "rdf:predicate": [
            "shortDescription"
          ]
        },
        {
          "@id": "https://data.datatourisme.fr/2134d071-c8d9-374a-b97d-82e2db7ab478",
          "dc:contributor": [
            "https://api.deepl.com/v2/translate"
          ],
          "rdf:language": [
            "es"
          ],
          "rdf:predicate": [
            "shortDescription"
          ]
        },
        {
          "@id": "https://data.datatourisme.fr/47ceb80a-1744-325b-a00b-30f3b66443de",
          "dc:contributor": [
            "https://api.deepl.com/v2/translate"
          ],
          "rdf:language": [
            "it"
          ],
          "rdf:predicate": [
            "shortDescription"
          ]
        },
        {
          "@id": "https://data.datatourisme.fr/49b5321d-b349-3a65-b5ec-595c2b09e7f8",
          "dc:contributor": [
            "https://api.deepl.com/v2/translate"
          ],
          "rdf:language": [
            "nl"
          ],
          "rdf:predicate": [
            "shortDescription"
          ]
        },
        {
          "@id": "https://data.datatourisme.fr/939f4201-539e-384b-a8b6-bc02dbbe34b7",
          "dc:contributor": [
            "https://api.deepl.com/v2/translate"
          ],
          "rdf:language": [
            "en"
          ],
          "rdf:predicate": [
            "shortDescription"
          ]
        }
      ],
      "shortDescription": {
        "de": [
          "Wanderung mit dem elektrischen Mountainbike. Geschichte und Kulturerbe des Capcir, Treffen mit Einwohnern und Erzeugern, Verkostung lokaler Produkte. Obligatorische Anmeldung bei Eco Bike, 07.87.71.64.72 Mountainbike, Helm und Betreuung inbegriffen. Kostenpflichtige Ausfahrt (65 e..."
        ],
        "en": [
          "Electric mountain bike tour. History and heritage of Capcir, meet local people and producers, taste local products. Registration required with Eco Bike, 07.87.71.64.72 VTTAE, helmet and supervision included. Paying excursion (65 e..."
        ],
        "it": [
          "Giro in mountain bike elettrica. Storia e patrimonio del Capcir, incontro con persone e produttori locali, degustazione di prodotti locali. È necessario iscriversi presso Eco Bike, 07.87.71.64.72 VTTAE, casco e supervisione inclusi. Quota di partecipazione (65 euro a persona)."
        ],
        "fr": [
          "Randonnée VTT électrique. Histoire et patrimoine du Capcir, rencontre d'habitant et de producteurs, dégustation de produits locaux. Inscriptions obligatoires auprès d'Eco Bike, 07.87.71.64.72 VTTAE, casque et encadrement compris. Sortie payante (65 e..."
        ],
        "es": [
          "Paseo en bicicleta eléctrica de montaña. Historia y patrimonio del Capcir, encuentro con la población y los productores locales, degustación de productos locales. Hay que inscribirse en Eco Bike, 07.87.71.64.72 VTTAE, casco y supervisión incluidos. Tarifa de pago (65 euros por persona)."
        ],
        "nl": [
          "Elektrische mountainbiketocht. Geschiedenis en erfgoed van de Capcir, ontmoet lokale mensen en producenten, proef lokale producten. Aanmelden bij Eco Bike, 07.87.71.64.72 VTTAE, helm en begeleiding inbegrepen. Kosten te betalen (65 euro per persoon)."
        ]
      }
    }
  ],
  "hasMainRepresentation": [
    {
      "@id": "https://data.datatourisme.fr/6bddf674-f856-3a32-b2ce-8d2172c85025",
      "ebucore:hasAnnotation": [
        {
          "@id": "https://data.datatourisme.fr/b2867aaf-3542-3f22-8971-118062dccff4",
          "ebucore:title": {
            "fr": [
              "capcir"
            ]
          },
          "@type": [
            "ebucore:Annotation"
          ],
          "credits": [
            "internet"
          ]
        }
      ],
      "ebucore:hasRelatedResource": [
        {
          "@id": "https://data.datatourisme.fr/8855f99c-6a7f-3d40-a3bc-6af35edb0e86",
          "ebucore:locator": [
            "https://cdt66.tourinsoft.com/upload/capcir.jpg"
          ],
          "@type": [
            "ebucore:Resource"
          ]
        }
      ],
      "@type": [
        "ebucore:EditorialObject"
      ]
    }
  ],
  "hasRepresentation": [
    {
      "@id": "https://data.datatourisme.fr/6bddf674-f856-3a32-b2ce-8d2172c85025",
      "ebucore:hasAnnotation": [
        {
          "@id": "https://data.datatourisme.fr/b2867aaf-3542-3f22-8971-118062dccff4",
          "ebucore:title": {
            "fr": [
              "capcir"
            ]
          },
          "@type": [
            "ebucore:Annotation"
          ],
          "credits": [
            "internet"
          ]
        }
      ],
      "ebucore:hasRelatedResource": [
        {
          "@id": "https://data.datatourisme.fr/8855f99c-6a7f-3d40-a3bc-6af35edb0e86",
          "ebucore:locator": [
            "https://cdt66.tourinsoft.com/upload/capcir.jpg"
          ],
          "@type": [
            "ebucore:Resource"
          ]
        }
      ],
      "@type": [
        "ebucore:EditorialObject"
      ]
    }
  ],
  "hasTranslatedProperty": [
    {
      "@id": "https://data.datatourisme.fr/0cf69b1c-f1ee-3781-8cc2-35e25d255fa1",
      "dc:contributor": [
        "https://api.deepl.com/v2/translate"
      ],
      "rdf:language": [
        "de"
      ],
      "rdf:predicate": [
        {
          "@id": "rdfs:comment"
        }
      ]
    },
    {
      "@id": "https://data.datatourisme.fr/4c42aeee-2d5e-350f-97c0-54dc9e96fefb",
      "dc:contributor": [
        "https://api.deepl.com/v2/translate"
      ],
      "rdf:language": [
        "nl"
      ],
      "rdf:predicate": [
        {
          "@id": "rdfs:comment"
        }
      ]
    },
    {
      "@id": "https://data.datatourisme.fr/5b9396cf-8334-3a13-a18b-016d3699b787",
      "dc:contributor": [
        "https://api.deepl.com/v2/translate"
      ],
      "rdf:language": [
        "es"
      ],
      "rdf:predicate": [
        {
          "@id": "rdfs:comment"
        }
      ]
    },
    {
      "@id": "https://data.datatourisme.fr/9975f9b5-740b-394c-80a8-9aade4687d97",
      "dc:contributor": [
        "https://api.deepl.com/v2/translate"
      ],
      "rdf:language": [
        "it"
      ],
      "rdf:predicate": [
        {
          "@id": "rdfs:comment"
        }
      ]
    },
    {
      "@id": "https://data.datatourisme.fr/b4e928f0-ee46-357e-a069-d8f6f1343fad",
      "dc:contributor": [
        "https://api.deepl.com/v2/translate"
      ],
      "rdf:language": [
        "en"
      ],
      "rdf:predicate": [
        {
          "@id": "rdfs:comment"
        }
      ]
    }
  ],
  "isLocatedAt": [
    {
      "@id": "https://data.datatourisme.fr/0cad1dea-1980-3519-8d44-778928343b1c",
      "schema:address": [
        {
          "@id": "https://data.datatourisme.fr/10f33a6e-ac7e-36d5-a63d-843ff609543e",
          "schema:addressLocality": "Les Angles",
          "schema:postalCode": "66210",
          "@type": [
            "schema:PostalAddress",
            "PostalAddress"
          ],
          "hasAddressCity": {
            "@id": "kb:66004",
            "@type": [
              "City"
            ],
            "rdfs:label": {
              "de": [
                "Les Angles"
              ],
              "pt": [
                "Les Angles"
              ],
              "en": [
                "Les Angles"
              ],
              "it": [
                "Les Angles"
              ],
              "fr": [
                "Les Angles"
              ],
              "nl": [
                "Les Angles"
              ],
              "es": [
                "Les Angles"
              ]
            },
            "insee": "66004",
            "isPartOfDepartment": {
              "@id": "kb:France7666",
              "@type": [
                "Department"
              ],
              "rdfs:label": {
                "de": [
                  "Pyrénées-Orientales"
                ],
                "pt": [
                  "Pyrénées-Orientales"
                ],
                "en": [
                  "Pyrénées-Orientales"
                ],
                "it": [
                  "Pyrénées-Orientales"
                ],
                "fr": [
                  "Pyrénées-Orientales"
                ],
                "nl": [
                  "Pyrénées-Orientales"
                ],
                "es": [
                  "Pyrénées-Orientales"
                ]
              },
              "insee": "66",
              "isPartOfRegion": {
                "@id": "kb:France76",
                "@type": [
                  "Region"
                ],
                "rdfs:label": {
                  "de": [
                    "Occitanie"
                  ],
                  "pt": [
                    "Occitanie"
                  ],
                  "en": [
                    "Occitanie"
                  ],
                  "it": [
                    "Occitanie"
                  ],
                  "fr": [
                    "Occitanie"
                  ],
                  "nl": [
                    "Occitanie"
                  ],
                  "es": [
                    "Occitanie"
                  ]
                },
                "insee": "76",
                "isPartOfCountry": {
                  "@id": "kb:France",
                  "@type": [
                    "schema:Country"
                  ],
                  "rdfs:label": {
                    "de": [
                      "France",
                      "Frankreich"
                    ],
                    "pt": [
                      "França",
                      "France"
                    ],
                    "en": [
                      "France"
                    ],
                    "it": [
                      "France",
                      "Francia"
                    ],
                    "fr": [
                      "France"
                    ],
                    "nl": [
                      "France",
                      "Frankrijk"
                    ],
                    "es": [
                      "France",
                      "Francia"
                    ]
                  }
                }
              }
            }
          }
        }
      ],
      "schema:geo": {
        "@id": "https://data.datatourisme.fr/baffbb4e-6cbc-3b67-a8f3-2f594cdee979",
        "schema:latitude": "42.57747",
        "schema:longitude": "2.0723",
        "@type": [
          "schema:GeoCoordinates"
        ]
      },
      "@type": [
        "schema:Place",
        "Place"
      ]
    }
  ],
  "lastUpdate": "2025-06-10",
  "lastUpdateDatatourisme": "2025-06-11T03:20:10.595Z",
  "offers": [
    {
      "@id": "https://data.datatourisme.fr/b7ec028d-de97-34f5-8f76-083acceb74f8",
      "schema:priceSpecification": [
        {
          "@id": "https://data.datatourisme.fr/8bd60b47-218e-37f0-86f7-58f8a7e3d097",
          "schema:maxPrice": [
            "65"
          ],
          "schema:minPrice": [
            "65"
          ],
          "@type": [
            "schema:PriceSpecification",
            "PriceSpecification"
          ],
          "hasEligiblePolicy": [
            {
              "@id": "kb:BaseRateFullRate",
              "@type": [
                "PricingPolicy"
              ],
              "rdfs:label": {
                "de": [
                  "Basistarif – voller Tarif"
                ],
                "pt": [
                  "Preço de base — preço total"
                ],
                "en": [
                  "Base rate - full rate"
                ],
                "it": [
                  "Tariffa di base — tariffa intera"
                ],
                "fr": [
                  "Tarif de base - plein tarif"
                ],
                "es": [
                  "Tarifa básica - tarifa completa"
                ],
                "nl": [
                  "Basistarief - vol tarief"
                ]
              }
            }
          ],
          "hasPricingMode": [
            {
              "@id": "kb:PerDay",
              "@type": [
                "PricingMode"
              ],
              "rdfs:label": {
                "de": [
                  "Pro Tag"
                ],
                "pt": [
                  "Por dia"
                ],
                "en": [
                  "Per day"
                ],
                "it": [
                  "A giornata"
                ],
                "fr": [
                  "A la journée"
                ],
                "es": [
                  "Por día"
                ],
                "nl": [
                  "Per dag"
                ]
              }
            },
            {
              "@id": "kb:PerPerson",
              "@type": [
                "PricingMode"
              ],
              "rdfs:label": {
                "de": [
                  "Pro Person"
                ],
                "pt": [
                  "Por pessoa"
                ],
                "en": [
                  "Per person"
                ],
                "it": [
                  "Per persona"
                ],
                "fr": [
                  "Par personne"
                ],
                "es": [
                  "Por persona"
                ],
                "nl": [
                  "Per persoon"
                ]
              }
            }
          ],
          "name": {
            "fr": [
              "Plein tarif"
            ]
          }
        }
      ],
      "@type": [
        "schema:Offer",
        "Offer"
      ]
    }
  ],
  "reducedMobilityAccess": false,
  "takesPlaceAt": [
    {
      "@id": "https://data.datatourisme.fr/0e463fd1-e69f-3a85-be28-070d7e7e221f",
      "@type": [
        "Period"
      ],
      "endDate": "2025-08-05",
      "startDate": "2025-08-05",
      "startTime": "14:00:00"
    }
  ]
}